{
  "intro.compliance"  : "1.4",
  
  "lex.key"           : "2.12",

  "basic.def.odr"     : "3.2",
  "basic.fundamental" : "3.9.1",
  "basic.compound"    : "3.9.2",

  "conv"              : "4",
  
  "expr"              : "5",
  "expr.prim"         : "5.1",
  "expr.prim.general" : "5.1.1",
  "expr.prim.lambda"  : "5.1.2",

  "dcl.decl"          : "8",
  "dcl.name"          : "8.1",
  "dcl.ambig.res"     : "8.2",
  "dcl.meaning"       : "8.3",
  "dcl.fct"           : "8.3.5",

  "over"              : "13",
  "over.load"         : "13.1",
  "over.dcl"          : "13.2",
  "over.match"        : "13.3",
  "over.over"         : "13.4",
  "over.oper"         : "13.5",
  "over.call"         : "13.5.4",
  "over.built"        : "13.6",

  "temp"                  : "14",
  "temp.arg"              : "14.3",
  "temp.arg.type"         : "14.3.1",
  "temp.arg.nontype"      : "14.3.2",
  "temp.arg.template"     : "14.3.3",
  "temp.dcls"             : "14.5",
  "temp.class"            : "14.5.1",
  "temp.mem"              : "14.5.2",
  "temp.class.spec.match" : "14.5.5.1",
  "temp.class.order"      : "14.5.5.2",
  "temp.class.spec.mfunc" : "14.5.5.3",
  "temp.fct"              : "14.5.6",
  "temp.over.link"        : "14.5.6.1",
  "temp.func.order"       : "14.5.6.2",

  "temp.deduct"           : "14.8.2"
}
